sphinxcontrib/__init__.py
sphinxcontrib/swagger.py
sphinxcontrib/assets/openapi.html
sphinxcontrib_swagger-0.0.4.dist-info/LICENSE
sphinxcontrib_swagger-0.0.4.dist-info/METADATA
sphinxcontrib_swagger-0.0.4.dist-info/WHEEL
sphinxcontrib_swagger-0.0.4.dist-info/top_level.txt
sphinxcontrib_swagger-0.0.4.dist-info/RECORD
